mia_simexp_mcp/__init__.py
mia_simexp_mcp/server.py
mia_simexp_mcp/tools.py
mia_simexp_mcp-0.2.0.dist-info/METADATA
mia_simexp_mcp-0.2.0.dist-info/WHEEL
mia_simexp_mcp-0.2.0.dist-info/entry_points.txt
mia_simexp_mcp-0.2.0.dist-info/top_level.txt
mia_simexp_mcp-0.2.0.dist-info/RECORD
