Metadata-Version: 2.4
Name: mia-simexp-mcp
Version: 0.2.0
Summary: MCP server for mia-simexp - Terminal-to-AI communication with A2A session management
Author-email: Mia Isabelle <mia@example.com>, gerico1007 <gerico@jgwill.com>
License: MIT
Project-URL: Homepage, https://github.com/miadisabelle/simexp
Project-URL: Documentation, https://github.com/miadisabelle/simexp/tree/main/mia_simexp_mcp
Project-URL: Repository, https://github.com/miadisabelle/simexp.git
Project-URL: Issues, https://github.com/miadisabelle/simexp/issues
Keywords: mcp,simplenote,ai,a2a,session,browser-automation,claude
Classifier: Development Status :: 3 - Alpha
Classifier: Intended Audience :: Developers
Classifier: License :: OSI Approved :: MIT License
Classifier: Programming Language :: Python :: 3
Classifier: Programming Language :: Python :: 3.10
Classifier: Programming Language :: Python :: 3.11
Classifier: Programming Language :: Python :: 3.12
Classifier: Topic :: Internet :: WWW/HTTP
Classifier: Topic :: Utilities
Requires-Python: >=3.10
Requires-Dist: mia-simexp>=0.6.0
Requires-Dist: mia-anemoi>=0.1.0
Requires-Dist: mcp>=1.0.0
Requires-Dist: pydantic>=2.0
Provides-Extra: dev
Requires-Dist: pytest>=7.0; extra == "dev"
Requires-Dist: pytest-asyncio>=0.21.0; extra == "dev"
Requires-Dist: pytest-cov>=4.0; extra == "dev"
Requires-Dist: black>=23.0; extra == "dev"
Requires-Dist: ruff>=0.1.0; extra == "dev"
Requires-Dist: build>=1.0; extra == "dev"
Requires-Dist: twine>=4.0; extra == "dev"
